parasail/__init__.py
parasail/bindings_v1.py
parasail/bindings_v2.py
parasail/parasail.dll
parasail/include/parasail.h
parasail/include/parasail/cpuid.h
parasail/include/parasail/function_lookup.h
parasail/include/parasail/internal_altivec.h
parasail/include/parasail/internal_avx.h
parasail/include/parasail/internal_neon.h
parasail/include/parasail/internal_sse.h
parasail/include/parasail/io.h
parasail/include/parasail/matrix_lookup.h
parasail/include/parasail/memory.h
parasail/include/parasail/stats.h
parasail/include/parasail/matrices/blosum100.h
parasail/include/parasail/matrices/blosum30.h
parasail/include/parasail/matrices/blosum35.h
parasail/include/parasail/matrices/blosum40.h
parasail/include/parasail/matrices/blosum45.h
parasail/include/parasail/matrices/blosum50.h
parasail/include/parasail/matrices/blosum55.h
parasail/include/parasail/matrices/blosum60.h
parasail/include/parasail/matrices/blosum62.h
parasail/include/parasail/matrices/blosum65.h
parasail/include/parasail/matrices/blosum70.h
parasail/include/parasail/matrices/blosum75.h
parasail/include/parasail/matrices/blosum80.h
parasail/include/parasail/matrices/blosum85.h
parasail/include/parasail/matrices/blosum90.h
parasail/include/parasail/matrices/blosum_map.h
parasail/include/parasail/matrices/blosumn.h
parasail/include/parasail/matrices/dnafull.h
parasail/include/parasail/matrices/nuc44.h
parasail/include/parasail/matrices/pam10.h
parasail/include/parasail/matrices/pam100.h
parasail/include/parasail/matrices/pam110.h
parasail/include/parasail/matrices/pam120.h
parasail/include/parasail/matrices/pam130.h
parasail/include/parasail/matrices/pam140.h
parasail/include/parasail/matrices/pam150.h
parasail/include/parasail/matrices/pam160.h
parasail/include/parasail/matrices/pam170.h
parasail/include/parasail/matrices/pam180.h
parasail/include/parasail/matrices/pam190.h
parasail/include/parasail/matrices/pam20.h
parasail/include/parasail/matrices/pam200.h
parasail/include/parasail/matrices/pam210.h
parasail-1.3.4.dist-info/COPYING
parasail-1.3.4.dist-info/METADATA
parasail-1.3.4.dist-info/WHEEL
parasail-1.3.4.dist-info/top_level.txt
parasail-1.3.4.dist-info/RECORD
